src/__init__.py
src/porter/__about__.py
src/porter/__init__.py
src/porter/backup.py
src/porter/cli.py
src/porter/config.py
src/porter/docker_helpers.py
reside_porter-0.0.1.dist-info/METADATA
reside_porter-0.0.1.dist-info/WHEEL
reside_porter-0.0.1.dist-info/entry_points.txt
reside_porter-0.0.1.dist-info/licenses/LICENSE.txt
reside_porter-0.0.1.dist-info/RECORD
