Metadata-Version: 2.1
Name: reside-porter
Version: 0.0.1
Summary: Tool to backup docker volumes
Project-URL: Documentation, https://github.com/reside-ic/porter#readme
Project-URL: Issues, https://github.com/reside-ic/porter/issues
Project-URL: Source, https://github.com/reside-ic/porter
Author-email: Alex <alex.hill@gmail.com>
License-Expression: MIT
License-File: LICENSE.txt
Classifier: Development Status :: 4 - Beta
Classifier: Programming Language :: Python
Classifier: Programming Language :: Python :: 3.7
Classifier: Programming Language :: Python :: 3.8
Classifier: Programming Language :: Python :: 3.9
Classifier: Programming Language :: Python :: 3.10
Classifier: Programming Language :: Python :: 3.11
Classifier: Programming Language :: Python :: Implementation :: CPython
Classifier: Programming Language :: Python :: Implementation :: PyPy
Requires-Python: >=3.7
Requires-Dist: docker
Requires-Dist: docopt
Requires-Dist: fabric
